src/__init__.py
src/pipeline.py
geo_pipeline-1.0.3.dist-info/METADATA
geo_pipeline-1.0.3.dist-info/WHEEL
geo_pipeline-1.0.3.dist-info/entry_points.txt
geo_pipeline-1.0.3.dist-info/top_level.txt
geo_pipeline-1.0.3.dist-info/RECORD
