Metadata-Version: 2.1
Name: geo-pipeline
Version: 1.0.3
Summary: NCBI GEO data extraction pipeline
Home-page: https://github.com/aausek/GEO_Pipeline
Author: Ana Ausek
Author-email: UNKNOWN
License: MIT
Platform: UNKNOWN
